{
  "meta": {
    "fetched_at": "2026-05-01T11:08:34.057141",
    "source": "NSE + Yahoo Finance + Screener.in + Trendlyne",
    "version": "v2",
    "is_live": true
  },
  "stress": {
    "nifty_level": 23997.55,
    "dd_ath_pct": 9.01,
    "dd_52w_pct": 9.01,
    "vix": 18.46,
    "dist_200dma_pct": -4.4,
    "pe_ratio": 28.64,
    "pe_10y_avg": 22.5,
    "pe_vs_avg_pct": 27.3
  },
  "breadth": {
    "ad_ratio": null,
    "advances": null,
    "declines": null,
    "pct_above_50dma": 64.1,
    "new_52w_highs": null,
    "new_52w_lows": null,
    "momentum_gap_50dma": -0.58,
    "pcr": null,
    "max_pain": null,
    "options_expiry": null
  },
  "structure": {
    "nifty50": {
      "level": 23997.55,
      "dd_ath_pct": 9.01,
      "dd_52w_pct": 9.01,
      "dma200": 25101.17,
      "dma50": 24137.63
    },
    "midcap150": {
      "level": 69643.9,
      "dd_ath_pct": 10.62,
      "dd_52w_pct": 2.65,
      "dma200": 68127.84,
      "dma50": 67214.59
    },
    "smallcap250": {
      "level": 18007.15,
      "dd_ath_pct": 0.5,
      "dd_52w_pct": 0.5,
      "dma200": null,
      "dma50": null
    }
  },
  "macro": {
    "brent_usd": 111.21,
    "us10y_yield": 4.39,
    "dxy": 98.03,
    "usdinr": 94.88,
    "fii_today_cr": null,
    "dii_today_cr": null,
    "fii_30d_cr": null,
    "eps_trend": "Stable"
  },
  "recovery": {
    "recent_low": 22679.4,
    "rally_from_low_pct": 5.81,
    "higher_low": false,
    "vix_trend": "Flat",
    "vix_peak": 25.52,
    "rsi_weekly": 41.9,
    "breadth_up_days": 0.8
  }
}